pybci/__init__.py
pybci/pybci.py
pybci/version.py
pybci/Configuration/EpochSettings.py
pybci/Configuration/FeatureSettings.py
pybci/Configuration/PseudoDeviceSettings.py
pybci/Configuration/__init__.py
pybci/ThreadClasses/AsyncDataReceiverThread.py
pybci/ThreadClasses/ClassifierThread.py
pybci/ThreadClasses/DataReceiverThread.py
pybci/ThreadClasses/FeatureProcessorThread.py
pybci/ThreadClasses/MarkerThread.py
pybci/ThreadClasses/OptimisedDataReceiverThread.py
pybci/ThreadClasses/__init__.py
pybci/Utils/Classifier.py
pybci/Utils/FeatureExtractor.py
pybci/Utils/LSLScanner.py
pybci/Utils/Logger.py
pybci/Utils/PseudoDevice.py
pybci/Utils/__init__.py
install_pybci-1.1.1.dist-info/LICENSE
install_pybci-1.1.1.dist-info/METADATA
install_pybci-1.1.1.dist-info/WHEEL
install_pybci-1.1.1.dist-info/top_level.txt
install_pybci-1.1.1.dist-info/RECORD
